myAI
