Metadata-Version: 1.0
Name: myAI
Version: 0.2.0
Summary: An artificial intelligence written in Python
Home-page: https://bitbucket.org/bkvaluemeal/myai
Author: Justin Willis
Author-email: sirJustin.Willis@gmail.com
License: ISC License
Platform: UNKNOWN
